mariantranslate/__init__.py
mariantranslate/translator.py
mariantranslate-0.1.8.dist-info/LICENSE
mariantranslate-0.1.8.dist-info/METADATA
mariantranslate-0.1.8.dist-info/WHEEL
mariantranslate-0.1.8.dist-info/top_level.txt
mariantranslate-0.1.8.dist-info/RECORD
