Metadata-Version: 2.1
Name: mariantranslate
Version: 0.1.8
Summary: Simple translator using Marian NMT.
Home-page: https://github.com/galuhsahid/mariantranslate
Author: Galuh Sahid
Author-email: galuh.sahid@protonmail.com
License: MIT
Keywords: translation,translator,translate,language,marian,nmt
Platform: UNKNOWN
Requires-Python: >=3.6.0
License-File: LICENSE
Requires-Dist: transformers (>=4.9.2)
Requires-Dist: sentencepiece (>=0.1.96)
Requires-Dist: torch (>=1.9.0)
Provides-Extra: dev
Requires-Dist: black (>=21.4b0) ; extra == 'dev'
Requires-Dist: isort (>=5.5.4) ; extra == 'dev'
Requires-Dist: flake8 (>=3.8.3) ; extra == 'dev'
Requires-Dist: pytest (>=6.2.4) ; extra == 'dev'
